yt_summarizer
