Metadata-Version: 2.1
Name: yt-summarizer
Version: 0.1.4
Summary: Python script to extract video transcripts based on the video id, and summarize the text content using the GPT-3.5 Turbo model.
Home-page: https://github.com/isaacduong/youtube_summarizer
Author: Isaac Duong
Author-email: isaaacduong@gmail.com
License: MIT
License-File: LICENSE
